<?xml version="1.0" encoding="utf-8"?>
  <odoo>
    <data>
      <!-- Campos nuevos en la interface de CRM -->
        <record id="inherit_fields_form" model="ir.ui.view">
          <field name="name">inherit.fields.form</field>
          <field name="model">crm.lead</field>
          <field name="inherit_id" ref="crm.crm_case_form_view_oppor"/>
          <field name="arch" type="xml">
            <xpath expr="//field[@name='tag_ids']" position="after">
              <field name="marca"/>
              <field name="target"/>
            </xpath>
          </field>
        </record>

        <record id="inherit_name_page" model="ir.ui.view">
          <field name="name">inherit.name.page</field>
          <field name="model">crm.lead</field>
          <field name="inherit_id" ref="crm.crm_case_form_view_oppor"/>
          <field name="arch" type="xml">
            <xpath expr="//form[1]/sheet[1]/notebook[1]//page[1]" position="attributes">
              <attribute name="string">Mecanica</attribute>
            </xpath>
          </field>
        </record>

        <record id="invisible_planned" model="ir.ui.view">
          <field name="name">inherit.invisible.planned</field>
          <field name="model">crm.lead</field>
          <field name="inherit_id" ref="crm.quick_create_opportunity_form"/>
          <field name="arch" type="xml">
            <xpath expr="//field[@name='planned_revenue']" position="attributes">
              <attribute name="invisible">1</attribute>
            </xpath>
          </field>
        </record>

      <!-- Domain para contador ODT -->    
        <record id="action_odt_crm" model="ir.actions.act_window">
                  <field name="name">ODT</field>
                  <field name="res_model">odt.crm</field>
                  <field name="view_mode">kanban,tree,form,graph,pivot</field>
                  <field name="domain">[('crm_odt_id', '=', active_id)]</field>
                  <field name="context">{'search_default_crm_odt_id': active_id, 'default_crm_odt_id': active_id}</field>
        </record>
      <!-- Domain para contador ODT -->

      <!-- Vista Kanban -->
        <record id="todo_task_kanban" model="ir.ui.view">
        <field name="model">odt.crm</field>
        <field name="arch" type="xml">
          <kanban default_group_by="stage_id" class="o_kanban_small_column" >
                  <field name="stage_id"/>
                  <field name="color"/>
                  <field name="kanban_state"/>
                  <field name="priority"/>
                  <field name="user_id"/>
                  <progressbar field="kanban_state" colors='{"planned": "success", "today": "warning", "overdue": "danger"}' help="This bar allows to filter the opportunities based on scheduled activities."/>
                        <templates>
                          <t t-name="kanban-box">
                            <div t-attf-class="#{kanban_getcolor(record.color.raw_value)} oe_kanban_global_click">
                              <div class="o_dropdown_kanban dropdown">
                                  <a class="dropdown-toggle o-no-caret btn" role="button" data-toggle="dropdown" href="#" aria-label="Dropdown menu" title="Dropdown menu">
                                      <span class="fa fa-ellipsis-v"/>
                                  </a>
                                  <div class="dropdown-menu" role="menu">
                                      <t t-if="widget.editable"><a role="menuitem" type="edit" class="dropdown-item">Edit</a></t>
                                      <t t-if="widget.deletable"><a role="menuitem" type="delete" class="dropdown-item">Delete</a></t>
                                      <ul class="oe_kanban_colorpicker" data-field="color"/>
                                  </div>
                              </div>
                              <div class="oe_kanban_content">
                                   <div>
                                        <strong class="o_kanban_record_title"><field name="name"/></strong>
                                   </div>
                                    <div>
                                        <field name="tag_ids" widget="many2many_tags" options="{'color_field': 'color'}"/>
                                    </div>
                                    <div class="o_kanban_record_bottom">
                                        <div class="oe_kanban_bottom_left">
                                            <field name="priority" widget="priority"/>
                                        </div>
                                        <div class="oe_kanban_bottom_right">
                                            <img t-att-src="kanban_image('res.users', 'image_small', record.user_id.raw_value)" t-att-title="record.user_id.value" t-att-alt="record.user_id.value" width="24" height="24" class="oe_kanban_avatar"/>
                                        </div>
                                    </div>
                            </div>
                            <div class="oe_clear">
                            </div>
                            </div>
                          </t>
                        </templates>
            </kanban>
          </field>
        </record>

<!-- End Vista Kanban -->

<!-- Formulario para vista kanban -->

      <record id="form_odt_crm" model="ir.ui.view">
            <field name="name">odt.crm.lead.form</field>
            <field name="model">odt.crm</field>
            <field name="priority">20</field>
            <field name="arch" type="xml">
                <form string="ODT" class="o_opportunity_form">
                  <header><field name="stage_id" widget="statusbar"
                            options="{'clickable': '1', 'fold_field': 'fold'}"
                            domain="['|', ('team_id', '=', team_id), ('team_id', '=', False)]"
                            attrs="{'invisible': [('active', '=', False)]}"/></header>
                    <sheet>
                        <field name="active" invisible="1"/>
                        <div class="oe_title">
                            <label for="name" class="oe_edit_only"/>
                            <h1><field name="name" placeholder="e.g. Product Pricing"/></h1>
                        </div>
                        <group>
                            <group>
                                <field name="partner_id"
                                    string="Customer" domain="[('customer', '=', True)]"

                                />
                                <field name="is_blacklisted" invisible="1"/>
                                <field name="partner_is_blacklisted" invisible="1"/>
                                <label for="email_from" class="oe_inline"/>
                                <div class="o_row o_row_readonly">
                                    <i class="fa fa-ban" style="color: red;" role="img" title="This email is blacklisted for mass mailing"
                                        aria-label="Blacklisted" attrs="{'invisible': ['|', ('is_blacklisted', '=', False), ('partner_address_email', '!=', False)]}" groups="base.group_user"></i>
                                    <field name="email_from"
                                       attrs="{'invisible': [('partner_address_email', '!=', False)]}"
                                       string="Email"
                                       widget="email"/>
                                    <i class="fa fa-ban" style="color: red;" role="img" title="This email is blacklisted for mass mailing"
                                        aria-label="Blacklisted" attrs="{'invisible': ['|', ('partner_is_blacklisted', '=', False), ('partner_address_email', '=', False)]}" groups="base.group_user"></i>
                                    <field name="partner_address_email"
                                       attrs="{'invisible': [('partner_address_email', '==', False)]}"
                                       widget="email"
                                       string="Email"/>
                                </div>
                                <field name="partner_address_phone"
                                       attrs="{'invisible': [('partner_address_phone', '==', False)]}"
                                       readonly="1"
                                       widget="phone"
                                       string="Phone"/>
                                <field name="phone"
                                       attrs="{'invisible': [('partner_address_phone', '!=', False)]}"
                                       widget="phone"/>
                            </group>

                            <group>
                                <field name="date_deadline"/>
                            </group>

                            <group>
                                <field name="user_id" context="{'default_groups_ref': ['base.group_user', 'base.group_partner_manager', 'sales_team.group_sale_salesman_all_leads'], 'team_id': team_id}" domain="[('share', '=', False)]"/>
                                <field name="team_id" widget="selection"/>
                            </group>
                            <group>
                                <field name="priority" widget="priority"/>
                                <field name="tag_ids" widget="many2many_tags" options="{'color_field': 'color', 'no_create_edit': True}"/>
                                <field name="marca"/>
                                <field name="target"/>
                                <field name="area"/>
                                <field name="med_spot_tv_abierta" attrs="{'invisible': [('area','!=','7')]}"/>
                                <field name="med_aaee_tv" attrs="{'invisible': [('area','!=','7')]}"/>
                                <field name="med_spoteo_carriers" attrs="{'invisible': [('area','!=','7')]}"/>
                                <field name="med_net_televisa" attrs="{'invisible': [('area','!=','7')]}"/>
                                <field name="med_otros_net" attrs="{'invisible': [('area','!=','7')]}"/>
                                <field name="med_radio" attrs="{'invisible': [('area','!=','7')]}"/>
                                <field name="med_revista" attrs="{'invisible': [('area','!=','7')]}"/>
                                <field name="med_prensa" attrs="{'invisible': [('area','!=','7')]}"/>
                                <field name="med_ooh" attrs="{'invisible': [('area','!=','7')]}"/>
                                <field name="med_digital" attrs="{'invisible': [('area','!=','7')]}"/>
                                <field name="med_analisis" attrs="{'invisible': [('area','!=','7')]}"/>
                                <field name="lost_reason" attrs="{'invisible': [('active', '=', True)]}"/>
                                <field name="date_conversion" invisible="1"/>
                            </group>
                        </group>

                        <notebook colspan="4">
                        <page string="Internal Notes">
                            <field name="description"/>
                        </page>
                        <page name="lead" string="Followup">
                            <group>
                                <group string="Initial Contact Information">
                                    <field name="partner_name"/>
                                    <label for="street" string="Address"/>
                                    <div class="o_address_format">
                                        <field name="street" placeholder="Street..." class="o_address_street"/>
                                        <field name="street2" placeholder="Street 2..." class="o_address_street"/>
                                        <field name="city" placeholder="City" class="o_address_city"/>
                                        <field name="state_id" class="o_address_state" placeholder="State" options='{"no_open": True}'/>
                                        <field name="zip" placeholder="ZIP" class="o_address_zip"/>
                                        <field name="country_id" placeholder="Country" class="o_address_country" options='{"no_open": True, "no_create": True}'/>
                                    </div>
                                </group>

                                <group class="mt48">
                                    <label for="contact_name"/>
                                    <div class="o_row">
                                        <field name="contact_name"/>
                                        <field name="title" placeholder="Title" domain="[]" options='{"no_open": True}'/>
                                    </div>
                                    <field name="function"/>
                                    <field name="mobile"/>
                                </group>
                                <group string="Marketing">
                                    <field name="campaign_id" />
                                    <field name="medium_id" />
                                    <field name="source_id" />
                                </group>
                                <group string="Misc" name="Misc">
                                    <field name="day_open" groups="base.group_no_one"/>
                                    <field name="day_close" groups="base.group_no_one"/>
                                    <field name="referred"/>
                                    <field name="type" invisible="1"/>
                                </group>
                            </group>
                        </page>
                        <page name="brief" string="Brief">
                                      <group name="left">
                                                  <group name="brief">
                                                      <field name="product"/>
                                                      <field name="project"/>
                                                      <field name="term_promo_date"/>
                                                      <field name="temporalidad"/>
                                                      <field name="slogan_marca"/>
                                                      <field name="logo_marca"/>
                                                  </group>
                                                  <group name="reto_proyecto" string="Reto del Proyecto">
                                                      <field name="rp_1" />
                                                      <field name="rp_2" />
                                                      <field name="rp_3" />
                                                      <field name="rp_4" />
                                                  </group>
                                                  <group name="objetivo_negocio" string="Objetivo del Negocio">
                                                      <field name="on_1" />
                                                      <field name="on_2" />
                                                      <field name="on_3" />
                                                      <field name="on_4" />
                                                  </group>
                                                  <group name="objetivo_marca"  string="Objetivo de la Marca">
                                                      <field name="ob_1" />
                                                      <field name="ob_2" />
                                                      <field name="ob_3" />
                                                  </group>
                                                  <group name="caracter_marca" string="Caracter de la Marca">
                                                      <field name="cm_1" />
                                                      <field name="cm_2" />
                                                      <field name="cm_3" />
                                                      <field name="cm_4" />
                                                  </group>
                                              </group>
                                              <group name="right">
                                                  <group name="competidores">
                                                      <field name="qcs_1"/>
                                                      <field name="qcs_2"/>
                                                      <field name="qcs_3"/>
                                                  </group>
                                                  <group name="dialogo">
                                                      <field name="vh_1"/>
                                                      <field name="vh_2"/>
                                                      <field name="vh_3"/>
                                                  </group>
                                                  <group name="comunicar">
                                                      <field name="dc_1"/>
                                                      <field name="dc_2"/>
                                                      <field name="dc_3"/>
                                                  </group>
                                                  <group name="no_comunicar?">
                                                      <field name="qc_1"/>
                                                      <field name="qc_2"/>
                                                  </group>  
                                                  <group name="ccp">
                                                    <field name="ccp_1"/>
                                                    <field name="ccp_2"/>
                                                  </group>
                                                  <group name="quiz_11" string="¿CÓMO Y DÓNDEVAMOS A COMUNICAR EL PROYECTO?">
                                                    <field name="cdp_1"/>
                                                    <field name="cdp_2"/>
                                                    <field name="cdp_3"/>
                                                  </group>
                                                  <group name="quiz_12">
                                                     <field name="qz_12"/>
                                                     <field name="qz_13"/>
                                                     <field name="qz_14"/>
                                                     <field name="qz_15"/>
                                                     <field name="qz_16"/>
                                                  </group>
                                          </group>
                        </page>

                        <!-- Page BTL/PDV en ODT -->
                        <page name="btl" string="BTL/PDV"  attrs="{'invisible': [('area','!=','1')]}" >
                          <group>
                                <group>
                                  <h3>Activacion</h3>
                                    <field name="personal"/>
                                    <field name="coverage"/>
                                </group>
                                     <page name="mat_elabor" string="Material a Elaborar">
                                        <field name="tabla_material_btl" widget="one2many_list">
                                          <tree editable="bottom">
                                              <field name = "tipo_material" />
                                              <field name = "quantity" />
                                              <field name = "medidas_formatos" />
                                          </tree>
                                          </field>
                                          <field name="descrption" placeholder="Descripcion"/>
                                    </page>
                                <group string="Tipo de solicitud">
                                    <field name="activation"/>
                                    <field name="mystery_shopper"/>
                                    <field name="promotoria" />
                                    <field name="sumpling"/>
                                    <field name="production_material"/>
                                    <field name="production_promocionales"/>
                                </group>
                              <group>
                                <h3>Puntos de Venta</h3>
                                <field name="vigencia"/>
                                <field name="activ_days"/>
                                <field name="auto_servicio"/>
                                <field name="departament"/>
                                <field name="centro_comercial"/>
                                <field name="calle"/>
                                <field name="otros"/>
                                <field name="others" attrs="{'invisible': [('otros','!=',True)]}"/>
                                <field name="listado_tiendas" />
                                <field name="material_apoyo"/>
                                <field name="comentarios_add"/>
                              </group>
                          </group> 
                              <group string="Cotizacion">                               
                                <page name="cotizacion_interna_btl" string="Cotizacion">
                                <field name="propiedad"/>
                                    <field name="tabla_cotizacion_btl" widget="one2many_list">
                                      <tree editable="bottom">
                                          <field name="concepto"/>
                                          <field name="cantidad"/>
                                          <field name="dias"/>
                                          <field name="semanas"/>
                                          <field name="precio_unitario_btl" widget="monetary" />
                                          <field name="costo_proveedor_btl" widget="monetary" />
                                      </tree>
                                    </field>
                                    <group>
                                      <group class="oe_subtotal_footer oe_right" name="totales">
                                        <field name="total_precio_unitario_btl" class="oe_subtotal_footer_separator" readonly="1"/>
                                        <field name="total_costo_proveedor_btl" class="oe_subtotal_footer_separator" readonly="1"/>
                                      </group>
                                    </group>
                                </page>
                              </group>
                                <group>
                                  <field name="btl"/>
                                  <field name="firma1_btl" widget="signature"/>
                                  <field name="firma2_btl" widget="signature"/>                                  
                                </group>
                        </page>

                        <!-- Page Produccion en ODT -->
                        <page name="production" string="Produccion"  attrs="{'invisible': [('area','!=','2')]}">
                          <group>
                            <group>
                                <h3>Tipo de Solicitud</h3>
                                <field name="p_spot_radio"/>
                                <field name="p_spot_tv"/>
                                <field name="p_spot_tv1"/>
                                <field name="p_cap_digital"/>
                                <field name="p_cineminuto"/>
                                <field name="p_lev_imagen"/>
                                <field name="p_pieca"/>
                                <field name="p_super"/>
                                <field name="p_shooting_photo"/>
                                <field name="p_edicion_video"/>
                              </group>
                              <group>
                               <field name="p_post_video"/>
                               <field name="p_cortinilla"/>
                               <field name="p_reel"/>
                               <field name="p_render"/>
                               <field name="p_locucion"/>
                               <field name="p_edicion_audio"/>
                               <field name="p_gif"/>
                               <field name="p_ftp"/>
                               <field name="p_otros"/>
                               <field name="p_otro_text" attrs="{'invisible': ('p_otros','=',False)}"/>  
                              </group>  
                              <group>
                                <field name="duracion"/>
                                <field name="tipo_trabajo"/>
                                <field name="descripcion"/>
                              </group>
                              <br/>
                                  <page name="mat_elabor" string="Material a Elaborar">
                                      <field name="tabla_material_produccion" widget="one2many_list">
                                        <tree editable="bottom">
                                            <field name = "tipo_material" />
                                            <field name = "medidas_formatos" />
                                        </tree>
                                        </field>
                                  </page>
                          </group>
                          <br/>
                          <h3>Cotizacion</h3>
                          <br/>
                          <group>
                            <page name="cotizacion_interna_produ" string="Cotizacion">
                                <field name="tabla_cotizacion_produccion" widget="one2many_list">
                                  <tree editable="bottom">
                                      <field name="concepto"/>
                                      <field name="cantidad"/>
                                      <field name="dias" />
                                      <field name="precio_uni_cliente" widget="monetary"/>
                                      <field name="costo_cliente" widget="monetary" />
                                      <field name="precio_uni_gtvp" widget="monetary" />
                                      <field name="pago_terceros" widget="monetary"/>
                                      <field name="costo_interno" widget="monetary"/>
                                      <field name="recuperacion" widget="monetary"/>
                                  </tree>
                                </field>
                                <group>
                                  <group class="oe_subtotal_footer oe_right" name="totales">
                                    <field name="total_cliente_produ" class="oe_subtotal_footer_separator" readonly="1"/>
                                    <field name="total_gtvo_produ" class="oe_subtotal_footer_separator" readonly="1"/>
                                    <field name="total_terceros_produ" class="oe_subtotal_footer_separator" readonly="1"/>
                                    <field name="total_interno_produ" class="oe_subtotal_footer_separator" readonly="1"/>
                                    <field name="total_recuperacion_produ" class="oe_subtotal_footer_separator" readonly="1"/>
                                  </group>
                                </group>
                            </page>
                          </group>
                          <group>
                            <field name="produccion"/>
                            <field name="firma1_prod" widget="signature"/>
                            <field name="firma2_prod" widget="signature"/>
                          </group>
                        </page>

                        <!-- Page Design en ODT -->
                        <page name="desing" string="Diseño"  attrs="{'invisible': [('area','!=','3')]}">
                          <group>
                            <group>
                              <h3>Tipo de solicitud</h3>
                              <field name="d_presentacion"/>
                              <field name="d_template"/>
                              <field name="d_master_graph"/>
                              <field name="d_adaptacion_pop"/>
                              <field name="d_adaptacion_digital"/>
                            </group>
                            <group>
                              <field name="d_adaptacion_ooh"/>
                              <field name="d_logotipo"/>
                              <field name="d_presentacion"/>
                              <field name="d_otro"/>
                              <field name="d_otro_desc" attrs="{'invisible': [('d_otro','=',False)]}"/>
                            </group>
                              <h3>Material a elaborar</h3><br/>
                              <page name="mat_elabor" string="Material a Elaborar">
                                  <field name="tabla_material_diseno" widget="one2many_list">
                                    <tree editable="bottom">
                                        <field name="tipo_material" />
                                        <field name="medidas" />
                                        <field name="formatos"/>
                                    </tree>
                                    </field>
                              </page>                               
                            <field name="dc_especificacion" placeholder="Comentarios y especificaciones"/>
                          </group>
                            <group>
                                <page name="cotizacion_interna_diseno" string="Cotizacion">
                                    <field name="tabla_cotizacion_produccion" widget="one2many_list">
                                      <tree editable="bottom">
                                          <field name="concepto"/>
                                          <field name="cantidad"/>
                                          <field name="dias" />
                                          <field name="precio_uni_cliente" widget="monetary"/>
                                          <field name="costo_cliente" widget="monetary" />
                                          <field name="precio_uni_gtvp" widget="monetary" />
                                          <field name="pago_terceros" widget="monetary"/>
                                          <field name="costo_interno" widget="monetary"/>
                                          <field name="recuperacion" widget="monetary"/>
                                      </tree>
                                    </field>
                                    <group>
                                      <group class="oe_subtotal_footer oe_right" name="totales">
                                        <field name="total_cliente_diseno" class="oe_subtotal_footer_separator" readonly="1"/>
                                        <field name="total_gtvo_diseno" class="oe_subtotal_footer_separator" readonly="1"/>
                                        <field name="total_terceros_diseno" class="oe_subtotal_footer_separator" readonly="1"/>
                                        <field name="total_interno_diseno" class="oe_subtotal_footer_separator" readonly="1"/>
                                        <field name="total_recuperacion_diseno" class="oe_subtotal_footer_separator" readonly="1"/>
                                      </group>
                                    </group>
                                </page>
                            </group> 
                            <group>
                              <field name="diseño_creatividad"/>
                              <field name="firma1_design" widget="signature"/>
                              <field name="firma2_design" widget="signature"/>
                            </group>
                        </page>
                       
                        <!-- Page Estrategia en ODT -->
                        <page name="estrategia" string="Estrategia" attrs="{'invisible': [('area','!=','9')]}">
                          <group>
                            <group>
                              <field name="e_conc_promo"/>
                              <field name="e_conc_camp"/>
                              <field name="e_mec_promv"/>
                              <field name="e_estr_difu"/>
                              <field name="e_guion_10"/>
                              <field name="e_guion_r20"/>
                              <field name="e_guion_r30"/>
                              <field name="e_guion_cineminuto"/>
                            </group>
                            <group>
                              <field name="e_guion_capsula"/>
                              <field name="e_copy"/>
                              <field name="e_slogan"/>
                              <field name="e_naming"/>
                              <field name="e_mailing"/>
                              <field name="e_creat_BTL"/>
                              <field name="e_concept"/>
                              <field name="e_otros"/>
                              <field name="e_otro_text" attrs="{'invisible': [('e_otros','=',False)]}"/> 
                              <field name="e_more_details"/>
                            </group>
                          </group>
                          <page name="cotizacion_interna_estrategia" string="Cotizacion">
                                        <field name="tabla_cotizacion_estrategia" widget="one2many_list">
                                          <tree editable="bottom">
                                              <field name="concepto"/>
                                              <field name="cantidad"/>
                                              <field name="dias" />
                                              <field name="precio_uni_cliente" widget="monetary"/>
                                              <field name="costo_cliente" widget="monetary" />
                                              <field name="precio_uni_gtvp" widget="monetary" />
                                              <field name="pago_terceros" widget="monetary"/>
                                              <field name="costo_interno" widget="monetary"/>
                                              <field name="recuperacion" widget="monetary"/>
                                          </tree>
                                        </field>
                                        <group>
                                          <group class="oe_subtotal_footer oe_right" name="totales">
                                            <field name="total_cliente_estrategia" class="oe_subtotal_footer_separator" readonly="1"/>
                                            <field name="total_gtvo_estrategia" class="oe_subtotal_footer_separator" readonly="1"/>
                                            <field name="total_terceros_estrategia" class="oe_subtotal_footer_separator" readonly="1"/>
                                            <field name="total_interno_estrategia" class="oe_subtotal_footer_separator" readonly="1"/>
                                            <field name="total_recuperacion_estrategia" class="oe_subtotal_footer_separator" readonly="1"/>
                                          </group>
                                        </group>
                                    </page>
                              <group>
                                <field name="estrategia"/>
                                <field name="firma1_estrategia" widget="signature"/>
                                <field name="firma2_estrategia" widget="signature"/>
                              </group>
                            </page>

                        <!-- Page Gestoria en ODT -->
                        <page name="gestoria" string="Gestoria"  attrs="{'invisible': [('area','!=','4')]}">
                          <group>
                            <group string="Sorteo">
                                <field name="gl_date_sorteo"/>
                                <field name="site_sorteo"/>
                                <field name="description_premio"/>
                                <field name="description_by_premio"/>
                                <field name="valor_primio"/>
                                <field name="lugar_enterga_premio"/>
                                <field name="dates_hrs_entrega"/>
                                <field name="responsable_promo"/>
                                <field name="dl_comments"/>                              
                            </group>
                            <group string="Concurso">
                                <field name="clave_proyecto"/>
                                <field name="social_reason"/>
                                <field name="respons_promocion"/>
                                <field name="respons_trato_personal"/>
                                <field name="name_promo"/>
                                <field name="geo_cobertura"/>
                                <field name="vigencia_promo"/>
                            </group>
                            <group string="Tipo de Promocion">
                                <field name="dl_sorteo"/>
                                <field name="gl_concurso"/>
                                <field name="gr_rtc"/>
                            </group>
                            <group>
                                <field name="gl_canje"/>
                                <field name="gl_otra"/>
                            </group>
                            <group string="Sorteo">
                                <field name="gl_vigencia_permiso"/>
                                <h4>Modalidad: </h4>
                                <field name="gl_talon_boleto"/>
                                <field name="gl_electr_boleto"/>
                                <field name="gl_formacion_num"/>
                            </group>
                            <group>
                                <field name="gl_sistema_info"/>
                                <field name="gl_sorteo_insta"/>
                            </group>
                            <group string="Concurso">
                                <field name="gl_cal_gana"/>
                                <field name="gl_predeterminado"/>
                                <field name="gl_juego_linea"/>
                                <field name="gl_mayor_puntaje"/>
                                <field name="gl_con_otro"/>
                            </group>
                            <group string="Contratacion de Servicios Notariales">
                              <field name='cert_foios'/>
                              <field name='det_ganadores'/>
                              <field name='entrega_premio'/>
                            </group>
                            <group>                          
                                <field name="gl_description_premio"/>
                                <field name="gl_mecanica"/>
                                <field name="gl_date_sorteo"/>
                            </group>
                            <group string="Preiodicos para publicar ganadores (sorteo)">
                              <field name="universal"/>
                              <field name="excelsior"/>
                              <field name="novedades"/>
                              <field name="la_prensa"/>
                              <field name="el_record"/>
                              <field name="publimetro"/>
                              <field name="esto"/>
                              <field name="jornada"/>
                              <field name="gl_preiodico_otros"/>
                            </group>
                            <group>
                              <field name="pagina_web"/>
                              <field name="extra"/>
                              <field name="gl_observations"/>
                            </group>
                          </group>
                            <group>
                                <page name="cotizacion_interna_diseno" string="Cotizacion">
                                    <field name="tabla_cotizacion_gestoria" widget="one2many_list">
                                      <tree editable="bottom">
                                          <field name="concepto"/>
                                          <field name="cantidad"/>
                                          <field name="precio_uni_gtvp" widget="monetary"/>
                                          <field name="costo_cliente" widget="monetary" />
                                          <field name="pago_terceros" widget="monetary" />
                                          <field name="costo_venta_cliente" widget="monetary"/>
                                      </tree>
                                    </field>
                                    <group>
                                      <group class="oe_subtotal_footer oe_right" name="totales">
                                        <field name="total_cliente_gestoria" class="oe_subtotal_footer_separator" readonly="1"/>
                                        <field name="total_gtvo_gestoria" class="oe_subtotal_footer_separator" readonly="1"/>
                                        <field name="total_terceros_gestoria" class="oe_subtotal_footer_separator" readonly="1"/>
                                      </group>
                                    </group>
                                </page> 
                            </group>
                            <group>
                              <field name="gestoria"/>
                              <field name="firma1_gestoria" widget="signature"/>
                              <field name="firma2_gestoria" widget="signature"/>
                            </group>
                        </page>

                        <!-- Page de logistica en ODT -->
                        <page name="logistica" string="Logistica" attrs="{'invisible': [('area','!=','8')]}">
                          <group>
                            <group>
                              <field name="tipo_promo"/>
                              <field name="mecanica_partici"/>
                              <field name="total_ganador"/>
                              <field name="total_premio"/>
                              <field name="total_ganador_premio"/>
                            </group>
                            <group>
                              <field name="valor_premio"/>
                              <field name="caract_premio"/>
                              <field name="vigencia_promo"/>
                              <field name="geo_cobertura"/>
                            </group>
                            <field name="firma1_logistica" widget="signature"/>
                            <field name="firma2_logistica" widget="signature"/>
                          </group>
                        </page>
                        
                        <!-- Page de Contact Center en ODT -->
                        <page name="callcenter" string="Contact Center"  attrs="{'invisible': [('area','!=','5')]}">
                          <group>  
                            <group string="Plataforma de Servicio">
                              <field name="cc_telefono"/>
                              <field name="cc_whats"/>                                
                              <field name="cc_email"/>
                              <field name="cc_twitter"/>
                              <field name="cc_face"/>
                              <field name="cc_chat"/>                           
                              <field name="cc_escritorio"/>
                              <field name="cc_otro" />
                              <field name="cc_especificar" attrs="{'invisible': [('cc_otro','=',False)]}"/>
                            </group>

                            <group string="Teléfono" attrs="{'invisible': [('cc_telefono','=',False)]}">
                              <field name="tipo_servicio1"/>                            
                              <field name="dictaminacion1" attrs="{'invisible':[('tipo_servicio1','!=','5')]}"/>
                              <group attrs="{'invisible':[('tipo_servicio1','=','5')]}" >
                                <field name="lunes1"/> 
                                <field name="martes1"/> 
                                <field name="miercoles1"/> 
                                <field name="jueves1"/> 
                                <field name="viernes1"/> 
                                <field name="sabado1"/> 
                                <field name="domingo1"/> 
                                <field name="festivos1"/> 
                                <field name="atencionstart1" widget="float_time"/> 
                                <field name="atencionend1" widget="float_time"/> 
                              </group>
                            </group>

                            <group string="WhatsApp" attrs="{'invisible': [('cc_whats','=',False)]}">
                              <field name="tipo_servicio2"/>
                              <field name="dictaminacion2" attrs="{'invisible':[('tipo_servicio2','!=','5')]}"/>
                              <group attrs="{'invisible':[('tipo_servicio1','=','5')]}" >
                                <field name="lunes2"/> 
                                <field name="martes2"/> 
                                <field name="miercoles2"/> 
                                <field name="jueves2"/> 
                                <field name="viernes2"/> 
                                <field name="sabado2"/> 
                                <field name="domingo2"/> 
                                <field name="festivos2"/> 
                                <field name="atencionstart2" widget="float_time"/> 
                                <field name="atencionend2" widget="float_time"/> 
                              </group>
                            </group>

                            <group string="E-mail" attrs="{'invisible': [('cc_email','=',False)]}">
                              <field name="tipo_servicio3"/>
                              <field name="dictaminacion3" attrs="{'invisible':[('tipo_servicio3','!=','5')]}"/>
                              <group attrs="{'invisible':[('tipo_servicio1','=','5')]}" >
                                <field name="lunes3"/> 
                                <field name="martes3"/> 
                                <field name="miercoles3"/> 
                                <field name="jueves3"/> 
                                <field name="viernes3"/> 
                                <field name="sabado3"/> 
                                <field name="domingo3"/> 
                                <field name="festivos3"/> 
                                <field name="atencionstart3" widget="float_time"/> 
                                <field name="atencionend3" widget="float_time"/> 
                              </group>
                            </group>

                            <group string="Twitter" attrs="{'invisible': [('cc_twitter','=',False)]}">
                              <field name="tipo_servicio4"/>
                              <field name="dictaminacion4" attrs="{'invisible':[('tipo_servicio4','!=','5')]}"/>
                              <group attrs="{'invisible':[('tipo_servicio1','=','5')]}" >
                                <field name="lunes4"/> 
                                <field name="martes4"/> 
                                <field name="miercoles4"/> 
                                <field name="jueves4"/> 
                                <field name="viernes4"/> 
                                <field name="sabado4"/> 
                                <field name="domingo4"/> 
                                <field name="festivos4"/> 
                                <field name="atencionstart4" widget="float_time"/> 
                                <field name="atencionend4" widget="float_time"/> 
                              </group>
                            </group>

                            <group string="Facebook" attrs="{'invisible': [('cc_face','=',False)]}">
                              <field name="tipo_servicio5"/>
                              <field name="dictaminacion5" attrs="{'invisible':[('tipo_servicio5','!=','5')]}"/>
                              <group attrs="{'invisible':[('tipo_servicio1','=','5')]}" >
                                <field name="lunes5"/> 
                                <field name="martes5"/> 
                                <field name="miercoles5"/> 
                                <field name="jueves5"/> 
                                <field name="viernes5"/> 
                                <field name="sabado5"/> 
                                <field name="domingo5"/> 
                                <field name="festivos5"/> 
                                <field name="atencionstart5" widget="float_time"/> 
                                <field name="atencionend5" widget="float_time"/> 
                              </group>                             
                            </group>

                            <group string="Chat" attrs="{'invisible': [('cc_chat','=',False)]}">
                              <field name="tipo_servicio6"/>
                              <field name="dictaminacion6" attrs="{'invisible':[('tipo_servicio6','!=','5')]}"/>
                              <group attrs="{'invisible':[('tipo_servicio1','=','5')]}" >
                                <field name="lunes6"/> 
                                <field name="martes6"/> 
                                <field name="miercoles6"/> 
                                <field name="jueves6"/> 
                                <field name="viernes3"/> 
                                <field name="sabado6"/> 
                                <field name="domingo6"/> 
                                <field name="festivos6"/> 
                                <field name="atencionstart6" widget="float_time"/> 
                                <field name="atencionend6" widget="float_time"/> 
                              </group>                              
                            </group>

                            <group string="Escritorio" attrs="{'invisible': [('cc_escritorio','=',False)]}">
                              <field name="tipo_servicio7"/>
                              <field name="dictaminacion7" attrs="{'invisible':[('tipo_servicio7','!=','5')]}"/>
                              <group attrs="{'invisible':[('tipo_servicio1','=','5')]}" >
                                <field name="lunes7"/> 
                                <field name="martes7"/> 
                                <field name="miercoles7"/> 
                                <field name="jueves7"/> 
                                <field name="viernes7"/> 
                                <field name="sabado7"/> 
                                <field name="domingo7"/> 
                                <field name="festivos7"/> 
                                <field name="atencionstart7" widget="float_time"/> 
                                <field name="atencionend7" widget="float_time"/> 
                              </group>                              
                            </group>

                            <group string="Otro" attrs="{'invisible': [('cc_otro','=',False)]}">
                              <field name="tipo_servicio8"/>
                              <field name="dictaminacion8" attrs="{'invisible':[('tipo_servicio8','!=','5')]}"/>
                              <group attrs="{'invisible':[('tipo_servicio1','=','5')]}" >
                                <field name="lunes8"/> 
                                <field name="martes8"/> 
                                <field name="miercoles8"/> 
                                <field name="jueves8"/> 
                                <field name="viernes8"/> 
                                <field name="sabado8"/> 
                                <field name="domingo8"/> 
                                <field name="festivos8"/> 
                                <field name="atencionstart8" widget="float_time"/> 
                                <field name="atencionend8" widget="float_time"/> 
                              </group>                              
                            </group>  
                           <field name="firma1_contact" widget="signature"/> 
                           <field name="firma2_contact" widget="signature"/>                           
                          </group>
                        </page>

                        <!-- Page de Marketing Digital en ODT -->
                        <page name="digital" string="Marketing Digital"  attrs="{'invisible': [('area','!=','6')]}">
                          <group colspan="3" >
                            <group string="Tipo de solicitud">
                              <field name="dg_web"/>
                              <field name="dg_aplications"/>
                              <field name="dg_social_net"/>
                              <field name="dg_pautadg"/>
                              <field name="dg_promoweb"/>
                              <field name="dg_estrategi"/>
                            </group>
                            <group string="Pagina Web" >
                              <group>
                                <field name="dg_mantenimiento"/>
                                <field name="dg_galeria"/>
                                <field name="dg_camara"/>
                                <field name="dg_calendar"/>
                                <field name="dg_otro"/>
                                <field name="dg_otro_detalle" attrs="{'invisible': [('dg_otro','=',False)]}"/>
                              </group>
                              <group>
                                <field name="dg_sistema_votacion"/>
                                <field name="dg_registro"/>
                                <field name="dg_newsletter"/>
                                <field name="dg_trivias"/>
                                <field name="dg_aplications_realtime"/>
                                <field name="dg_galeria_video"/>
                              </group>
                            </group>

                            <group string="Video Juegos / Aplicaciones">
                              <field name="dg_descripcion_va"/>
                              <field name="n_niveles"/>
                              <field name="dg_opt_1" />
                              <field name="dg_opt_2" />
                              <field name="dg_opt_3" />
                              <field name="dg_opt_4" />
                              <field name="dg_opt_5" />
                              <field name="dg_opt_6" />
                            </group>
                            <group string="Redes Sociales">
                              <field name="dg_opt_7"/>
                              <field name="dg_opt_8"/>
                              <field name="dg_opt_9"/>
                              <field name="dg_opt_10"/>
                              <field name="dg_opt_11"/>
                              <field name="dg_opt_12"/>
                              <field name="dg_opt_13"/>
                              <field name="dg_opt_14"/>
                              <field name="dg_propuesta"/>
                            </group>
                            <group string="Pauta Digital">
                              <field name="dg_presupuesto"/>
                              <field name="dg_objetivos"/>
                              <field name="dg_alcance"/>
                              <field name="dg_banner"/>
                              <field name="dg_observations"/>
                            </group>
                            <group string="Promoweb">
                              <field name="dg_opt_15"/>
                              <field name="dg_opt_16"/>
                              <field name="dg_opt_17"/>
                              <field name="dg_opt_18"/>
                              <field name="dg_opt_19"/>
                            </group>
                            <group string="Subcontrataciones">
                              <field name="dg_opt_20"/>
                              <field name="dg_opt_21"/>
                              <field name="dg_opt_22"/>
                              <field name="dg_sub_detalle" attrs="{'invisible': [('dg_opt_22','=',False)]}" />
                            </group>
                            <group string="Extras">
                              <field name="dg_opt_23"/>
                              <field name="dg_opt_24"/>
                              <field name="dg_cant_codigos"/>
                              <field name="dg_cant_digitos"/>
                              <field name="dg_opt_25"/>
                              <field name="dg_opt_26"/>
                              <field name="dg_otros"/>
                              <field name="dg_descr"/>
                            </group>
                          </group>
                            <group>
                                <page name="cotizacion_interna_diseno" string="Cotizacion">
                                    <field name="tabla_cotizacion_digital" widget="one2many_list">
                                      <tree editable="bottom">
                                          <field name="concepto"/>
                                          <field name="periodo"/>
                                          <field name="cantidad" />
                                          <field name="meses"/>
                                          <field name="horas"/>
                                          <field name="costo_hora" widget="monetary" />
                                          <field name="costo_interno" widget="monetary"/>
                                          <field name="pago_terceros" widget="monetary"/>
                                          <field name="recuperacion" widget="monetary"/>
                                          <field name="costo_cliente" widget="monetary"/>
                                          <field name="monto_venta" widget="monetary"/>
                                      </tree>
                                    </field>
                                    <group>
                                      <group class="oe_subtotal_footer oe_right" name="totales">
                                        <field name="total_costo_interno_digital" class="oe_subtotal_footer_separator" readonly="1"/>
                                        <field name="total_pago_terceros_digital" class="oe_subtotal_footer_separator" readonly="1"/>
                                        <field name="total_recuperacion_digital" class="oe_subtotal_footer_separator" readonly="1"/>
                                        <field name="total_costo_cliente_digital" class="oe_subtotal_footer_separator" readonly="1"/>
                                        <field name="total_monto_venta_digital" class="oe_subtotal_footer_separator" readonly="1"/>
                                      </group>
                                    </group>
                                </page> 
                            </group>
                            <group>
                              <field name="digital"/>
                              <field name="firma1_digital" widget="signature"/>
                              <field name="firma2_digital" widget="signature"/>
                            </group>
                        </page>

                        <!-- Page de Medios en ODT -->
                        <page name="medios" string="Medios"  attrs="{'invisible': [('area','!=','7')]}">
                          <group>
                            <group>
                              <h4>Para uso Exclusivo de Medios</h4>
                              <field name="med_folio"/>
                              <field name="med_fecha_soli"/>
                              <field name="med_hora_soli"  widget="float_time"/>
                              <field name="med_fecha_entrega"/>
                              <field name="med_fecha_real"/>
                              <field name="med_elabora"/>
                              <field name="med_nivel_complejidad"/>
                            </group>
                            <group string="ODT Medios">
                              <field name="med_odt_fecha_entrega"/>
                              <field name="med_clave_proyecto"/>
                              <field name="med_tipo_trabajo"/>
                            </group>
                            <group>
                              <field name="med_objetivo_comunicacion"/>
                              <field name="med_periodo_camap"/>
                              <field name="med_tipo_analisis"/>
                              <field name="med_oberv_generales"/>
                              <field name="med_solicita"/>
                              <field name="med_getente"/>
                              <field name="med_dirc_comercial"/>
                              <field name="med_icepresidencia"/>
                            </group>
                          </group>
                        </page>

                        <page name="medios_tv_abierta" string="Spot TV Abierta TVSA" attrs="{'invisible': [('med_spot_tv_abierta','=',False)]}">
                          <group string="Solicitud plan de Medios/ Televisa Spoteo TV Abierta Nacional y/o Local">
                            <group>
                              <field name="tvsa_tipo_camp"/>
                              <field name="tvsa_otro"/>
                              <field name="tvsa_catego_televisa"/>
                              <field name="tvsa_nse"/>
                            <h3>Grupos de Edad</h3>
                              <field name="tvsa_grupo_edad_1"/>
                              <field name="tvsa_grupo_edad_2"/>
                              <field name="tvsa_grupo_edad_3"/>
                              <field name="tvsa_grupo_edad_4"/>
                              <field name="tvsa_grupo_edad_5"/>
                              <field name="tvsa_grupo_edad_6"/>
                              <field name="tvsa_grupo_edad_otro"/>
                            <h3>Sexo</h3>
                              <field name="tvsa_sexo_p"/>
                              <field name="tvsa_sexo_m"/>
                              <field name="tvsa_sexo_h"/>
                            <h3>Rol Familiar</h3>
                              <field name="tvsa_rol_family"/>
                            <h3>Resp. Niños</h3>
                              <field name="years_03"/>
                              <field name="years_48"/>
                              <field name="years_912"/>
                              <field name="target_secundario"/>
                            </group>
                            <group>
                            <h3>Abierta Nacional</h3>
                              <field name="duracion_spot"/>
                              <field name="opcion_compra"/>
                              <field name="mixto_proporcion"/>
                              <field name="target_compra_modulo"/>
                              <field name="target_especial"/>
                              <field name="cofepris"/>
                              <field name="a_favor"/>
                              <field name="kids_policy"/>
                              <field name="sptv_periodo_camp1"/>
                            <h3>Canales Módulos o Franjas siempore serán 2, 5 y3</h3>
                              <field name="canal_1"/>
                              <field name="canal_2"/>
                              <field name="canal_3"/>
                              <field name="tvsa_abierta"/>
                            <h3>Tv Abierta Local</h3>
                              <field name="tv_abierta_duracion_spot"/>
                              <field name="canal_local"/>
                              <field name="bloqueos"/>
                              <field name="sptv_periodo_camp2"/>
                              <field name="foro_tv"/>
                              <field name="foro_tv_descrip"/>
                              <field name="monto_inverison_tvabierta"/>
                              <field name="tvsa_abierta_observaciones"/>
                            </group>
                          </group>
                        </page>

                        <page name="medios_aaeetv" string="AAEE TV TVSA" attrs="{'invisible': [('med_aaee_tv','=',False)]}">
                          <group>
                            <group>
                              <field name="aaee_categoria_televisa"/>
                              <field name="target_primario"/>
                              <field name="tarjet_secudario"/>
                              <field name="box_bool"/>
                              <field name="canal5_bool"/>
                              <field name="canal9_bool"/>
                              <field name="comedia_bool"/>
                              <field name="revista_bool"/>
                              <field name="deportivos_bool"/>
                              <field name="foro_tv_bool"/>
                              <field name="lucha_bool"/>
                              <field name="noticiero_bool"/>
                            </group>
                            <group>
                              <h3>TV Abierta Nacional</h3>
                              <field name="aaeetv_periodo_camp"/>
                              <field name="aaee_monto_maximo"/>
                              <field name="aaee_monto_minimo"/>
                              <h3>Canales Televisa</h3>
                              <field name="aaeetv_2"/>
                              <field name="aaeetv_5"/>
                              <field name="aaeetv_9"/>
                              <field name="aaeetv_foro_tv"/>
                              <field name="conoce_programas"/>
                            </group>
                            <group string="Box" attrs="{'invisible': [('box_bool','=',False)]}">
                              <field name="box_selection" />
                              <field name="box_text"/>
                            </group>
                            <group string="Canal 5" attrs="{'invisible': [('canal5_bool','=',False)]}">
                              <field name="canal5_selection"/>
                              <field name="canal5_text"/>
                            </group>
                            <group string="Canal 0" attrs="{'invisible': [('canal9_bool','=',False)]}">
                              <field name="canal9_selection"/>
                              <field name="canal9_text"/>
                            </group>
                            <group string="Comedia" attrs="{'invisible': [('comedia_bool','=',False)]}">
                              <field name="comedia_selection"/>
                              <field name="comedia_text"/>
                            </group>
                            <group string="Revista" attrs="{'invisible': [('revista_bool','=',False)]}">
                              <field name="revista_selection"/>
                              <field name="revista_text"/>
                            </group>
                            <group string="Deportivos" attrs="{'invisible': [('deportivos_bool','=',False)]}">
                              <field name="deportivos_selection"/>
                              <field name="deportivo_text"/>
                            </group>
                            <group string="Foro TV" attrs="{'invisible': [('foro_tv_bool','=',False)]}">
                              <field name="foro_tv_selection"/>
                              <field name="foro_tv_text"/>
                            </group>
                            <group string="Lucha Libre AAA" attrs="{'invisible': [('lucha_bool','=',False)]}">
                              <field name="lucha_libre_selection"/>
                              <field name="lucha_text"/>
                            </group>
                            <group string="Noticieros" attrs="{'invisible': [('noticiero_bool','=',False)]}">
                              <field name="noticieros_selection"/>
                              <field name="noticiero_text"/>
                            </group>
                            <group>
                              <h3>TV Abierta Local</h3>
                              <field name="aaeetv_abierta_local_periodo_camp"/>
                              <field name="aaeetv_abierta_monto_maximo"/>
                              <field name="aaeetv_abierta_monto_maximo"/>
                            </group>
                              <group>
                               <page name="cotizacion_interna_diseno" string="Cotizacion">
                                    <field name="tabla_plaza" widget="one2many_list">
                                      <tree editable="bottom">
                                          <field name="plaza"/>
                                          <field name="tipo_accion"/>
                                      </tree>
                                    </field>
                                </page> 
                              </group>
                             <field name="aaeee_observations" placeholder="Observaciones"/>
                            </group>
                        </page>

                        <page name="medios_brief" string="Brief AAEE" attrs="{'invisible': [('med_aaee_tv','=',False)]}">
                          <group>
                            <group>
                              <h3>Tipo de Soporte</h3>
                              <field name="tv_abierta_bool"/>
                              <field name="tv_local_bool"/>
                              <field name="Network_bool"/>
                            </group>
                            <group>
                              <field name="area_comercial_selection"/>
                              <field name="braa_elabora"/>
                              <field name="braa_fecha"/>
                              <field name="braa_periodo"/>
                              <field name="brief_presupuesto_minimo"/>
                              <field name="brief_presupuesto_maximo"/>
                            </group>
                            <group>
                              <field name="braa_nombre_proyecto"/>
                              <field name="braa_descripcion_personalidad"/>
                              <field name="braa_objetivo"/>
                              <field name="braa_idea_comunicar"/>
                              <field name="braa_ambiente_contexto"/>
                              <field name="braa_talento_personaje"/>
                              <field name="braa_propuesta_idea"/>
                            </group>
                            <group>
                              <h3>Tipo de programa</h3>
                              <field name="braa_opcion1"/>
                              <field name="braa_opcion2"/>
                              <field name="braa_opcion3"/>
                              <field name="braa_opcion4"/>
                              <field name="braa_opcion5"/>
                              <field name="braa_opcion6"/>
                              <field name="braa_opcion7"/>
                              <field name="braa_opcion8"/>
                              <field name="braa_opcion9"/>
                              <field name="braa_opcion10"/>
                              <field name="braa_programa_especifico"/>
                              <field name="braa_acciones"/>
                            </group>
                          </group>
                        </page>

                        <page name="medios_carriers" string="Spoteo Carriers" attrs="{'invisible': [('med_spoteo_carriers','=',False)]}">
                          <group>
                            <group>

                            </group>
                          </group>
                        </page>

                        <page name="medios_network" string="Network Televisa" attrs="{'invisible': [('med_net_televisa','=',False)]}">
                          <group>
                            <group>

                            </group>
                          </group>
                        </page>

                        <page name="medios_otro_net" string="Otros Networks" attrs="{'invisible': [('med_otros_net','=',False)]}">
                          <group>
                            <group>

                            </group>
                          </group>
                        </page>

                        <page name="medios_radio" string="Radio" attrs="{'invisible': [('med_radio','=',False)]}">
                          <group>
                            <group>

                            </group>
                          </group>
                        </page>

                        <page name="medios_revista" string="Revista" attrs="{'invisible': [('med_revista','=',False)]}">
                          <group>
                            <group>

                            </group>
                          </group>
                        </page>

                        <page name="medios_prensa" string="Prensa" attrs="{'invisible': [('med_prensa','=',False)]}">
                          <group>
                            <group>

                            </group>
                          </group>
                        </page>

                        <page name="medios_ooh" string="OOH" attrs="{'invisible': [('med_ooh','=',False)]}">
                          <group>
                            <group>

                            </group>
                          </group>
                        </page>

                        <page name="medios_digital" string="Digital" attrs="{'invisible': [('med_digital','=',False)]}">
                          <group>
                            <group>

                            </group>
                          </group>
                        </page>

                        <page name="medios_analisis" string="Analisis" attrs="{'invisible': [('med_analisis','=',False)]}">
                          <group>
                            <group>

                            </group>
                          </group>
                        </page>



<!-- 
<field name=""/>
<field name=""/>
<field name=""/>
<field name=""/>
<field name=""/>
<field name=""/>
<field name=""/>
<field name=""/>
<field name=""/>
<field name=""/>
<field name=""/>
<field name=""/>
<field name=""/>
<field name=""/>
<field name=""/>
<field name=""/>
<field name=""/>
<field name=""/>
<field name=""/>
<field name=""/>
<field name=""/>
<field name=""/>
<field name=""/>
<field name=""/>
<field name=""/>
<field name=""/>
<field name=""/>
<field name=""/>
<field name=""/>
<field name=""/>
<field name=""/>
<field name=""/>
<field name=""/>
<field name=""/>
<field name=""/>
<field name=""/>
<field name=""/>
<field name=""/>
<field name=""/>
<field name=""/>
<field name=""/>
<field name=""/>
<field name=""/>
<field name=""/>
<field name=""/>
<field name=""/>
<field name=""/>
<field name=""/>
<field name=""/>
<field name=""/>
<field name=""/>
<field name=""/>
<field name=""/>
<field name=""/>
<field name=""/>
<field name=""/>
<field name=""/>
<field name=""/>
<field name=""/>
<field name=""/>
<field name=""/>
<field name=""/>
<field name=""/>
<field name=""/>
<field name=""/>
<field name=""/>
<field name=""/>
<field name=""/>
-->

                        </notebook>
                    </sheet>
                    <div class="oe_chatter">
                       <field name="message_follower_ids" widget="mail_followers" groups="base.group_user"/>
                       <field name="activity_ids" widget="mail_activity"/>
                       <field name="message_ids" widget="mail_thread"/>
                    </div>
                </form>
            </field>
        </record>

<!-- Boton stat info para ODT -->
      
      <record id="inherit_button_box" model="ir.ui.view">
        <field name="name">inherit.button.box</field>
        <field name="model">crm.lead</field>
        <field name="inherit_id" ref="crm.crm_case_form_view_oppor"/>
        <field name="arch" type="xml">
          <xpath expr="//div[@class='oe_button_box']" position="inside">
                <button class="oe_stat_button" icon="fa-list" name="%(action_odt_crm)d" type="action">
                      <field name="odt_count" widget="statinfo" string="ODT"/>
               </button>
          </xpath>
          <xpath expr="//form[1]/sheet[1]//h2[1]" position="attributes">
            <attribute name="invisible">1</attribute>
          </xpath>
        </field>
      </record>

<!-- Boton stat info parar ODT -->     

      <record id="inherit_page" model="ir.ui.view">
        <field name="name">inherit.page</field>
        <field name="model">crm.lead</field>
        <field name="inherit_id" ref="crm.crm_case_form_view_oppor"/>
        <field name="arch" type="xml">
          <xpath expr="//form[1]/sheet[1]/notebook[1]" position="inside">
            <page name="brief" string="Brief">
              <group name="left">
                          <group name="brief">
                              <field name="product"/>
                              <field name="project"/>
                              <field name="term_promo_date"/>
                              <field name="temporalidad"/>
                              <field name="slogan_marca"/>
                              <field name="logo_marca"/>
                          </group>
                          <group name="reto_proyecto" string="Reto del Proyecto">
                              <field name="rp_1" />
                              <field name="rp_2" />
                              <field name="rp_3" />
                              <field name="rp_4" />
                          </group>
                          <group name="objetivo_negocio" string="Objetivo del Negocio">
                              <field name="on_1" />
                              <field name="on_2" />
                              <field name="on_3" />
                              <field name="on_4" />
                          </group>
                          <group name="objetivo_marca"  string="Objetivo de la Marca">
                              <field name="ob_1" />
                              <field name="ob_2" />
                              <field name="ob_3" />
                          </group>
                          <group name="caracter_marca" string="Caracter de la Marca">
                              <field name="cm_1" />
                              <field name="cm_2" />
                              <field name="cm_3" />
                              <field name="cm_4" />
                          </group>
                      </group>
                      <group name="right">
                          <group name="competidores">
                              <field name="qcs_1"/>
                              <field name="qcs_2"/>
                              <field name="qcs_3"/>
                          </group>
                          <group name="dialogo">
                              <field name="vh_1"/>
                              <field name="vh_2"/>
                              <field name="vh_3"/>
                          </group>
                          <group name="comunicar">
                              <field name="dc_1"/>
                              <field name="dc_2"/>
                              <field name="dc_3"/>
                          </group>
                          <group name="no_comunicar?">
                              <field name="qc_1"/>
                              <field name="qc_2"/>
                          </group>  
                          <group name="ccp">
                            <field name="ccp_1"/>
                            <field name="ccp_2"/>
                          </group>
                          <group name="quiz_11" string="¿CÓMO Y DÓNDEVAMOS A COMUNICAR EL PROYECTO?">
                            <field name="cdp_1"/>
                            <field name="cdp_2"/>
                            <field name="cdp_3"/>
                          </group>
                          <group name="quiz_12">
                             <field name="qz_12"/>
                             <field name="qz_13"/>
                             <field name="qz_14"/>
                             <field name="qz_15"/>
                             <field name="qz_16"/>
                          </group>
                  </group>
            </page>
            <page name="montos" string="Presupuesto Autorizado">
              <group string="Presupuestos por areas">
                <group>
                    <field name="btl" />
                    <field name="produccion" />
                    <field name="diseño_creatividad" />
                    <field name="gestoria_logistica" />
                    <field name="call_center"/>
                    <field name="digital"/>
                    <field name="medios"/>
                    <field name="logistica"/>
                    <field name="estrategia"/>
                </group>
              </group>
            </page>
          </xpath>
        </field>
      </record>

    <!-- Campos para tipos de Gatos -->

      <record id="inherit_account_column" model="ir.ui.view">
              <field name="name">inherit.account.column</field>
              <field name="model">sale.order</field>
              <field name="inherit_id" ref="sale.view_order_form"/>
              <field name="arch" type="xml">
                <xpath expr="//field[@name='order_line']/tree//field[@name='analytic_tag_ids']" position="after">
                  <field name='tipo_gasto'/>
                </xpath>
              </field>
      </record>
      <record id="inherit_page_finanza_project" model="ir.ui.view">
              <field name="name">inherit.finanza.page</field>
              <field name="model">project.project</field>
              <field name="inherit_id" ref="project.edit_project"/>
              <field name="arch" type="xml">
                <xpath expr="//form[1]/sheet[1]//notebook[1]" position="inside">
                  <page name="finanzas" string="Control Presupuestal">
                    <group>
                      <group>
                        <field name='ref_project'/>
                        <field name='odt'/>
                        <field name='fin_clave'/>
                        <field name='dates'/>
                        <field name='ref_customer'/>
                      </group>
                      <group>
                        <field name='u_bruta_p'/>
                        <field name='u_bruta_r'/>
                        <field name="total_pagar" readonly="1"/>
                            <!-- <field name=""/> -->
                      </group>
                      <group string='Gasto Aprovado'>
                          <field name='btl'/>
                          <field name='produccion'/>
                          <field name='diseño_creatividad'/>
                          <field name='gestoria_logistica'/>
                          <field name='call_center'/>
                          <field name='digital'/>
                          <field name='medios'/>
                      </group>
                      <group name="ingresos">
                            <page name="cotizacion_interna_diseno" string="Cotizacion">
                                <field name="tabla_gastos" widget="one2many_list">
                                  <tree editable="bottom">
                                      <field name='fac_gastos'/>
                                      <field name='disviacion'/>
                                  </tree>
                                </field>
                                <group>
                                </group>
                            </page> 
                      </group>
                      </group>
                  </page>                  
                </xpath>
              </field>
      </record>
  </data>
</odoo>